framefinder/__init__.py
framefinder/_modidx.py
framefinder/core.py
framefinder/examples.py
framefinder/framedimensions.py
framefinder/framelabels.py
framefinder/framestructure.py
framefinder-0.0.2.dist-info/LICENSE
framefinder-0.0.2.dist-info/METADATA
framefinder-0.0.2.dist-info/WHEEL
framefinder-0.0.2.dist-info/entry_points.txt
framefinder-0.0.2.dist-info/top_level.txt
framefinder-0.0.2.dist-info/RECORD
